LICENSE
MANIFEST.in
README.rst
setup.py
django_mptt_tree_editor.egg-info/PKG-INFO
django_mptt_tree_editor.egg-info/SOURCES.txt
django_mptt_tree_editor.egg-info/dependency_links.txt
django_mptt_tree_editor.egg-info/requires.txt
django_mptt_tree_editor.egg-info/top_level.txt
mptt_tree_editor/__init__.py
mptt_tree_editor/admin.py
mptt_tree_editor/models.py
mptt_tree_editor/settings.py
mptt_tree_editor/tests.py
mptt_tree_editor/views.py
mptt_tree_editor/locale/en/LC_MESSAGES/django.mo
mptt_tree_editor/locale/en/LC_MESSAGES/django.po
mptt_tree_editor/locale/es/LC_MESSAGES/django.mo
mptt_tree_editor/locale/es/LC_MESSAGES/django.po
mptt_tree_editor/locale/it/LC_MESSAGES/django.mo
mptt_tree_editor/locale/it/LC_MESSAGES/django.po
mptt_tree_editor/locale/pt/LC_MESSAGES/django.mo
mptt_tree_editor/locale/pt/LC_MESSAGES/django.po
mptt_tree_editor/locale/pt_BR/LC_MESSAGES/django.mo
mptt_tree_editor/locale/pt_BR/LC_MESSAGES/django.po
mptt_tree_editor/locale/ru/LC_MESSAGES/django.mo
mptt_tree_editor/locale/ru/LC_MESSAGES/django.po
mptt_tree_editor/static/mptt_tree_editor/fein_tree.css
mptt_tree_editor/static/mptt_tree_editor/fein_tree.js
mptt_tree_editor/static/mptt_tree_editor/ie_compat.js
mptt_tree_editor/static/mptt_tree_editor/jquery-1.7.1.min.js
mptt_tree_editor/static/mptt_tree_editor/jquery-ui-1.8.16.custom.min.js
mptt_tree_editor/static/mptt_tree_editor/jquery.cookie.js
mptt_tree_editor/static/mptt_tree_editor/style.css
mptt_tree_editor/static/mptt_tree_editor/toolbox.js
mptt_tree_editor/static/mptt_tree_editor/img/arrow-move.png
mptt_tree_editor/static/mptt_tree_editor/img/contenttypes.png
mptt_tree_editor/static/mptt_tree_editor/img/default-bg.gif
mptt_tree_editor/static/mptt_tree_editor/img/disclosure-down.png
mptt_tree_editor/static/mptt_tree_editor/img/disclosure-right.png
mptt_tree_editor/static/mptt_tree_editor/img/drag_order_circle.png
mptt_tree_editor/static/mptt_tree_editor/img/help.gif
mptt_tree_editor/static/mptt_tree_editor/img/icon-no.gif
mptt_tree_editor/static/mptt_tree_editor/img/icon-unknown.gif
mptt_tree_editor/static/mptt_tree_editor/img/icon-yes.gif
mptt_tree_editor/static/mptt_tree_editor/img/icon_addlink.gif
mptt_tree_editor/static/mptt_tree_editor/img/icon_deletelink.gif
