Metadata-Version: 1.1
Name: django-mptt-tree-editor
Version: 0.1.2
Summary: Provides FeinCMS's mptt admin tree editor as a separate app
Home-page: http://bitbucket.org/san/django-mptt-tree-editor
Author: Santiago Piccinini
Author-email: spiccinini@codigosur.org
License: BSD License
Platform: OS Independent
Classifier: Environment :: Web Environment
Classifier: Framework :: Django
Classifier: Intended Audience :: Developers
Classifier: License :: OSI Approved :: BSD License
Classifier: Operating System :: OS Independent
Classifier: Programming Language :: Python
Classifier: Programming Language :: Python :: 2.6
Classifier: Programming Language :: Python :: 2.7
Classifier: Topic :: Internet :: WWW/HTTP :: Dynamic Content
Classifier: Topic :: Software Development
Classifier: Topic :: Software Development :: Libraries
